{"price":140.17455462498785,"tip":7.008727731249393,"items":["Burger","Pizza","Fried Rice","Waffles","Naan","Aloo Paratha","Taco","Brownies"],"modeOfPayment":"Card","orderID":"15576862-c658-434f-a199-866a8dbf5195","restaurantID":"8962af0e-938a-49d0-9f40-2d71eb46aef1","driverID":"d18667d8-2d12-4926-ae55-0d845fe8e6ef","contactlessDelivery":false,"restLoc":{"lat":18.365244,"lon":76.912813},"custLoc":{"lat":18.387539,"lon":76.929829},"orderTime":{"hour":13,"minute":46,"second":51,"nano":0},"deliveredTime":{"hour":14,"minute":24,"second":51,"nano":0}}