{"price":39.36579874812013,"tip":1.9682899374060066,"items":["Momo","Fried Rice","Pizza","Waffles","Naan","Aloo Paratha","Idli","Paneer Butter Masala","Noodles"],"modeOfPayment":"Cash On Delivery","orderID":"278aa16b-00a4-4709-914e-283bebe7650d","restaurantID":"ecf752a3-59ca-4e6a-95dc-b20a2cd62c56","driverID":"625bb819-3b3b-4be8-8bf2-0f6b3826261f","contactlessDelivery":false,"restLoc":{"lat":19.414579,"lon":76.502089},"custLoc":{"lat":19.417716,"lon":76.510853},"orderTime":{"hour":23,"minute":52,"second":10,"nano":0},"deliveredTime":{"hour":0,"minute":30,"second":10,"nano":0}}