{"price":191.85723187692906,"tip":9.592861593846454,"items":["Pizza","Burger","Fried Rice","Waffles","Muffins","Pasta","Taco","Noodles","Brownies"],"modeOfPayment":"Card","orderID":"f91a5d7f-a48b-4804-b87a-1878e3832e08","restaurantID":"a7c52901-3b11-432d-8495-4b94defee7ed","driverID":"eb38dcd3-996f-4b3a-a6f8-2fd98a7e7c4f","contactlessDelivery":true,"restLoc":{"lat":12.666229,"lon":78.210093},"custLoc":{"lat":12.708142,"lon":78.177168},"orderTime":{"hour":20,"minute":42,"second":26,"nano":0},"deliveredTime":{"hour":21,"minute":20,"second":26,"nano":0}}