{"price":70.67499054062299,"tip":3.533749527031149,"items":["Momo","Waffles","Naan","Aloo Paratha","Dosa","Brownies","Noodles"],"modeOfPayment":"Card","orderID":"8ad6516d-60ee-4598-9e60-c6d0faf301d8","restaurantID":"3679cfc0-47e6-4d9b-b2a3-d83a8685e896","driverID":"10066470-4204-42da-83c2-094d727436d7","contactlessDelivery":false,"restLoc":{"lat":17.874361,"lon":76.4853},"custLoc":{"lat":17.881176,"lon":76.475234},"orderTime":{"hour":13,"minute":19,"second":5,"nano":0},"deliveredTime":{"hour":13,"minute":57,"second":5,"nano":0}}